dragon/__init__.py
dragon/cli.py
dragon/dragon_client.py
dragon/dragon_constants.py
dragon/dragon_pb2.py
dragon/dragon_pb2_grpc.py
dragon/dragon_server.py
dragon/dragon_services.py
dragon_orchestrator-0.1.dist-info/LICENSE
dragon_orchestrator-0.1.dist-info/METADATA
dragon_orchestrator-0.1.dist-info/WHEEL
dragon_orchestrator-0.1.dist-info/entry_points.txt
dragon_orchestrator-0.1.dist-info/top_level.txt
dragon_orchestrator-0.1.dist-info/RECORD
